{
	"archive" : {},
	"artifacts" : 
	[
		{
			"path" : "src/microsim/traffic_lights/libmicrosim_traffic_lights.a"
		}
	],
	"backtrace" : 1,
	"backtraceGraph" : 
	{
		"commands" : 
		[
			"add_library",
			"add_definitions",
			"include_directories"
		],
		"files" : 
		[
			"src/microsim/traffic_lights/CMakeLists.txt",
			"CMakeLists.txt"
		],
		"nodes" : 
		[
			{
				"file" : 0
			},
			{
				"command" : 0,
				"file" : 0,
				"line" : 68,
				"parent" : 0
			},
			{
				"file" : 1
			},
			{
				"command" : 1,
				"file" : 1,
				"line" : 334,
				"parent" : 2
			},
			{
				"command" : 2,
				"file" : 1,
				"line" : 428,
				"parent" : 2
			},
			{
				"command" : 2,
				"file" : 1,
				"line" : 429,
				"parent" : 2
			},
			{
				"command" : 2,
				"file" : 1,
				"line" : 341,
				"parent" : 2
			},
			{
				"command" : 2,
				"file" : 1,
				"line" : 377,
				"parent" : 2
			},
			{
				"command" : 2,
				"file" : 1,
				"line" : 411,
				"parent" : 2
			}
		]
	},
	"compileGroups" : 
	[
		{
			"compileCommandFragments" : 
			[
				{
					"fragment" : " -std=c++11 -pthread -Wall -pedantic -Wextra -g -D_DEBUG -fPIC   -I/usr/include/fox-1.6"
				}
			],
			"defines" : 
			[
				{
					"backtrace" : 3,
					"define" : "FLOAT_MATH_FUNCTIONS"
				}
			],
			"includes" : 
			[
				{
					"backtrace" : 4,
					"path" : "/home/tl/sumo/build/src"
				},
				{
					"backtrace" : 5,
					"path" : "/home/tl/sumo/src"
				},
				{
					"backtrace" : 6,
					"isSystem" : true,
					"path" : "/usr/include/freetype2"
				},
				{
					"backtrace" : 7,
					"isSystem" : true,
					"path" : "/usr/include/gdal"
				},
				{
					"backtrace" : 8,
					"isSystem" : true,
					"path" : "/usr/include/eigen3"
				}
			],
			"language" : "CXX",
			"sourceIndexes" : 
			[
				0,
				2,
				4,
				6,
				8,
				10,
				13,
				15,
				17,
				19,
				22,
				24,
				26,
				28,
				30,
				32,
				34,
				36,
				38,
				40,
				42,
				44,
				46,
				48,
				50,
				52,
				54,
				56,
				58,
				60,
				62
			]
		}
	],
	"id" : "microsim_traffic_lights::@6eacaf5005114980ea76",
	"name" : "microsim_traffic_lights",
	"nameOnDisk" : "libmicrosim_traffic_lights.a",
	"paths" : 
	{
		"build" : "src/microsim/traffic_lights",
		"source" : "src/microsim/traffic_lights"
	},
	"sourceGroups" : 
	[
		{
			"name" : "Source Files",
			"sourceIndexes" : 
			[
				0,
				2,
				4,
				6,
				8,
				10,
				13,
				15,
				17,
				19,
				22,
				24,
				26,
				28,
				30,
				32,
				34,
				36,
				38,
				40,
				42,
				44,
				46,
				48,
				50,
				52,
				54,
				56,
				58,
				60,
				62
			]
		},
		{
			"name" : "Header Files",
			"sourceIndexes" : 
			[
				1,
				3,
				5,
				7,
				9,
				11,
				12,
				14,
				16,
				18,
				20,
				21,
				23,
				25,
				27,
				29,
				31,
				33,
				35,
				37,
				39,
				41,
				43,
				45,
				47,
				49,
				51,
				53,
				55,
				57,
				59,
				61,
				63
			]
		}
	],
	"sources" : 
	[
		{
			"backtrace" : 1,
			"compileGroupIndex" : 0,
			"path" : "src/microsim/traffic_lights/MSActuatedTrafficLightLogic.cpp",
			"sourceGroupIndex" : 0
		},
		{
			"backtrace" : 1,
			"path" : "src/microsim/traffic_lights/MSActuatedTrafficLightLogic.h",
			"sourceGroupIndex" : 1
		},
		{
			"backtrace" : 1,
			"compileGroupIndex" : 0,
			"path" : "src/microsim/traffic_lights/MSDelayBasedTrafficLightLogic.cpp",
			"sourceGroupIndex" : 0
		},
		{
			"backtrace" : 1,
			"path" : "src/microsim/traffic_lights/MSDelayBasedTrafficLightLogic.h",
			"sourceGroupIndex" : 1
		},
		{
			"backtrace" : 1,
			"compileGroupIndex" : 0,
			"path" : "src/microsim/traffic_lights/MSOffTrafficLightLogic.cpp",
			"sourceGroupIndex" : 0
		},
		{
			"backtrace" : 1,
			"path" : "src/microsim/traffic_lights/MSOffTrafficLightLogic.h",
			"sourceGroupIndex" : 1
		},
		{
			"backtrace" : 1,
			"compileGroupIndex" : 0,
			"path" : "src/microsim/traffic_lights/MSRailSignal.cpp",
			"sourceGroupIndex" : 0
		},
		{
			"backtrace" : 1,
			"path" : "src/microsim/traffic_lights/MSRailSignal.h",
			"sourceGroupIndex" : 1
		},
		{
			"backtrace" : 1,
			"compileGroupIndex" : 0,
			"path" : "src/microsim/traffic_lights/MSRailSignalConstraint.cpp",
			"sourceGroupIndex" : 0
		},
		{
			"backtrace" : 1,
			"path" : "src/microsim/traffic_lights/MSRailSignalConstraint.h",
			"sourceGroupIndex" : 1
		},
		{
			"backtrace" : 1,
			"compileGroupIndex" : 0,
			"path" : "src/microsim/traffic_lights/MSRailSignalControl.cpp",
			"sourceGroupIndex" : 0
		},
		{
			"backtrace" : 1,
			"path" : "src/microsim/traffic_lights/MSRailSignalControl.h",
			"sourceGroupIndex" : 1
		},
		{
			"backtrace" : 1,
			"path" : "src/microsim/traffic_lights/MSPhaseDefinition.h",
			"sourceGroupIndex" : 1
		},
		{
			"backtrace" : 1,
			"compileGroupIndex" : 0,
			"path" : "src/microsim/traffic_lights/MSPhasedTrafficLightLogic.cpp",
			"sourceGroupIndex" : 0
		},
		{
			"backtrace" : 1,
			"path" : "src/microsim/traffic_lights/MSPhasedTrafficLightLogic.h",
			"sourceGroupIndex" : 1
		},
		{
			"backtrace" : 1,
			"compileGroupIndex" : 0,
			"path" : "src/microsim/traffic_lights/MSPushButton.cpp",
			"sourceGroupIndex" : 0
		},
		{
			"backtrace" : 1,
			"path" : "src/microsim/traffic_lights/MSPushButton.h",
			"sourceGroupIndex" : 1
		},
		{
			"backtrace" : 1,
			"compileGroupIndex" : 0,
			"path" : "src/microsim/traffic_lights/MSRailCrossing.cpp",
			"sourceGroupIndex" : 0
		},
		{
			"backtrace" : 1,
			"path" : "src/microsim/traffic_lights/MSRailCrossing.h",
			"sourceGroupIndex" : 1
		},
		{
			"backtrace" : 1,
			"compileGroupIndex" : 0,
			"path" : "src/microsim/traffic_lights/MSSimpleTrafficLightLogic.cpp",
			"sourceGroupIndex" : 0
		},
		{
			"backtrace" : 1,
			"path" : "src/microsim/traffic_lights/MSSimpleTrafficLightLogic.h",
			"sourceGroupIndex" : 1
		},
		{
			"backtrace" : 1,
			"path" : "src/microsim/traffic_lights/MSSOTLDefinitions.h",
			"sourceGroupIndex" : 1
		},
		{
			"backtrace" : 1,
			"compileGroupIndex" : 0,
			"path" : "src/microsim/traffic_lights/MSSOTLE2Sensors.cpp",
			"sourceGroupIndex" : 0
		},
		{
			"backtrace" : 1,
			"path" : "src/microsim/traffic_lights/MSSOTLE2Sensors.h",
			"sourceGroupIndex" : 1
		},
		{
			"backtrace" : 1,
			"compileGroupIndex" : 0,
			"path" : "src/microsim/traffic_lights/MSSOTLPolicyDesirability.cpp",
			"sourceGroupIndex" : 0
		},
		{
			"backtrace" : 1,
			"path" : "src/microsim/traffic_lights/MSSOTLPolicyDesirability.h",
			"sourceGroupIndex" : 1
		},
		{
			"backtrace" : 1,
			"compileGroupIndex" : 0,
			"path" : "src/microsim/traffic_lights/MSSOTLPolicy5DFamilyStimulus.cpp",
			"sourceGroupIndex" : 0
		},
		{
			"backtrace" : 1,
			"path" : "src/microsim/traffic_lights/MSSOTLPolicy5DFamilyStimulus.h",
			"sourceGroupIndex" : 1
		},
		{
			"backtrace" : 1,
			"compileGroupIndex" : 0,
			"path" : "src/microsim/traffic_lights/MSSOTLPolicy5DStimulus.cpp",
			"sourceGroupIndex" : 0
		},
		{
			"backtrace" : 1,
			"path" : "src/microsim/traffic_lights/MSSOTLPolicy5DStimulus.h",
			"sourceGroupIndex" : 1
		},
		{
			"backtrace" : 1,
			"compileGroupIndex" : 0,
			"path" : "src/microsim/traffic_lights/MSSOTLPolicy3DStimulus.cpp",
			"sourceGroupIndex" : 0
		},
		{
			"backtrace" : 1,
			"path" : "src/microsim/traffic_lights/MSSOTLPolicy3DStimulus.h",
			"sourceGroupIndex" : 1
		},
		{
			"backtrace" : 1,
			"compileGroupIndex" : 0,
			"path" : "src/microsim/traffic_lights/MSSOTLPolicy.cpp",
			"sourceGroupIndex" : 0
		},
		{
			"backtrace" : 1,
			"path" : "src/microsim/traffic_lights/MSSOTLPolicy.h",
			"sourceGroupIndex" : 1
		},
		{
			"backtrace" : 1,
			"compileGroupIndex" : 0,
			"path" : "src/microsim/traffic_lights/MSSOTLMarchingPolicy.cpp",
			"sourceGroupIndex" : 0
		},
		{
			"backtrace" : 1,
			"path" : "src/microsim/traffic_lights/MSSOTLMarchingPolicy.h",
			"sourceGroupIndex" : 1
		},
		{
			"backtrace" : 1,
			"compileGroupIndex" : 0,
			"path" : "src/microsim/traffic_lights/MSSOTLCongestionPolicy.cpp",
			"sourceGroupIndex" : 0
		},
		{
			"backtrace" : 1,
			"path" : "src/microsim/traffic_lights/MSSOTLCongestionPolicy.h",
			"sourceGroupIndex" : 1
		},
		{
			"backtrace" : 1,
			"compileGroupIndex" : 0,
			"path" : "src/microsim/traffic_lights/MSSOTLPhasePolicy.cpp",
			"sourceGroupIndex" : 0
		},
		{
			"backtrace" : 1,
			"path" : "src/microsim/traffic_lights/MSSOTLPhasePolicy.h",
			"sourceGroupIndex" : 1
		},
		{
			"backtrace" : 1,
			"compileGroupIndex" : 0,
			"path" : "src/microsim/traffic_lights/MSSOTLPlatoonPolicy.cpp",
			"sourceGroupIndex" : 0
		},
		{
			"backtrace" : 1,
			"path" : "src/microsim/traffic_lights/MSSOTLPlatoonPolicy.h",
			"sourceGroupIndex" : 1
		},
		{
			"backtrace" : 1,
			"compileGroupIndex" : 0,
			"path" : "src/microsim/traffic_lights/MSSOTLRequestPolicy.cpp",
			"sourceGroupIndex" : 0
		},
		{
			"backtrace" : 1,
			"path" : "src/microsim/traffic_lights/MSSOTLRequestPolicy.h",
			"sourceGroupIndex" : 1
		},
		{
			"backtrace" : 1,
			"compileGroupIndex" : 0,
			"path" : "src/microsim/traffic_lights/MSSOTLPolicyBasedTrafficLightLogic.cpp",
			"sourceGroupIndex" : 0
		},
		{
			"backtrace" : 1,
			"path" : "src/microsim/traffic_lights/MSSOTLPolicyBasedTrafficLightLogic.h",
			"sourceGroupIndex" : 1
		},
		{
			"backtrace" : 1,
			"compileGroupIndex" : 0,
			"path" : "src/microsim/traffic_lights/MSSOTLPhaseTrafficLightLogic.cpp",
			"sourceGroupIndex" : 0
		},
		{
			"backtrace" : 1,
			"path" : "src/microsim/traffic_lights/MSSOTLPhaseTrafficLightLogic.h",
			"sourceGroupIndex" : 1
		},
		{
			"backtrace" : 1,
			"compileGroupIndex" : 0,
			"path" : "src/microsim/traffic_lights/MSSOTLSensors.cpp",
			"sourceGroupIndex" : 0
		},
		{
			"backtrace" : 1,
			"path" : "src/microsim/traffic_lights/MSSOTLSensors.h",
			"sourceGroupIndex" : 1
		},
		{
			"backtrace" : 1,
			"compileGroupIndex" : 0,
			"path" : "src/microsim/traffic_lights/MSSOTLTrafficLightLogic.cpp",
			"sourceGroupIndex" : 0
		},
		{
			"backtrace" : 1,
			"path" : "src/microsim/traffic_lights/MSSOTLTrafficLightLogic.h",
			"sourceGroupIndex" : 1
		},
		{
			"backtrace" : 1,
			"compileGroupIndex" : 0,
			"path" : "src/microsim/traffic_lights/MSSOTLWaveTrafficLightLogic.cpp",
			"sourceGroupIndex" : 0
		},
		{
			"backtrace" : 1,
			"path" : "src/microsim/traffic_lights/MSSOTLWaveTrafficLightLogic.h",
			"sourceGroupIndex" : 1
		},
		{
			"backtrace" : 1,
			"compileGroupIndex" : 0,
			"path" : "src/microsim/traffic_lights/MSSOTLHiLevelTrafficLightLogic.cpp",
			"sourceGroupIndex" : 0
		},
		{
			"backtrace" : 1,
			"path" : "src/microsim/traffic_lights/MSSOTLHiLevelTrafficLightLogic.h",
			"sourceGroupIndex" : 1
		},
		{
			"backtrace" : 1,
			"compileGroupIndex" : 0,
			"path" : "src/microsim/traffic_lights/MSSwarmTrafficLightLogic.cpp",
			"sourceGroupIndex" : 0
		},
		{
			"backtrace" : 1,
			"path" : "src/microsim/traffic_lights/MSSwarmTrafficLightLogic.h",
			"sourceGroupIndex" : 1
		},
		{
			"backtrace" : 1,
			"compileGroupIndex" : 0,
			"path" : "src/microsim/traffic_lights/MSDeterministicHiLevelTrafficLightLogic.cpp",
			"sourceGroupIndex" : 0
		},
		{
			"backtrace" : 1,
			"path" : "src/microsim/traffic_lights/MSDeterministicHiLevelTrafficLightLogic.h",
			"sourceGroupIndex" : 1
		},
		{
			"backtrace" : 1,
			"compileGroupIndex" : 0,
			"path" : "src/microsim/traffic_lights/MSTLLogicControl.cpp",
			"sourceGroupIndex" : 0
		},
		{
			"backtrace" : 1,
			"path" : "src/microsim/traffic_lights/MSTLLogicControl.h",
			"sourceGroupIndex" : 1
		},
		{
			"backtrace" : 1,
			"compileGroupIndex" : 0,
			"path" : "src/microsim/traffic_lights/MSTrafficLightLogic.cpp",
			"sourceGroupIndex" : 0
		},
		{
			"backtrace" : 1,
			"path" : "src/microsim/traffic_lights/MSTrafficLightLogic.h",
			"sourceGroupIndex" : 1
		}
	],
	"type" : "STATIC_LIBRARY"
}
